{
    "tenantId": "as",
    "moduleName": "BPA",
    "Parapet": [
        {
            "id": 1,
            "occupancy": "residential",
            "parapetValueOne": 1.2,
            "parapetValueTwo": 1.5,
            "active": true
        },
        {
            "id": 2,
            "occupancy": "mercantile / commercial",
            "parapetValueOne": 1.2,
            "parapetValueTwo": 1.5,
            "active": true
        },
        {
            "id": 3,
            "occupancy": "industrial",
            "parapetValueOne": 1.2,
            "parapetValueTwo": 1.5,
            "active": true
        },
        {
            "id": 7,
            "occupancy": "educational",
            "parapetValueOne": 1.2,
            "parapetValueTwo": 1.5,
            "active": true
        },
        {
            "id": 4,
            "occupancy": "assembly",
            "parapetValueOne": 1.2,
            "parapetValueTwo": 1.5,
            "active": true
        },
        {
            "id": 5,
            "occupancy": "storage",
            "parapetValueOne": 1.2,
            "parapetValueTwo": 1.5,
            "active": true
        },
        {
            "id": 6,
            "occupancy": "factories",
            "parapetValueOne": 1.2,
            "parapetValueTwo": 1.5,
            "active": true
        }
    ]
}